{
  "page_info": {
    "url": "https://www.gymshark.com/products/gymshark-crest-straight-leg-joggers-black-aw23",
    "final_url": "https://www.gymshark.com/products/gymshark-crest-straight-leg-joggers-black-aw23",
    "status_code": 200,
    "canonical_url": "https://www.gymshark.com/products/gymshark-crest-straight-leg-joggers-black-aw23",
    "title": "Gymshark Crest Straight Leg Joggers - Black | Gymshark",
    "meta_description": "Shop the Crest Straight Leg Joggers in black. With next day delivery and free returns, shop online today at Gymshark.",
    "https": true,
    "load_time_ms": 616,
    "page_type": "PRODUCT",
    "crawl_timestamp": "2026-02-21T18:00:59.908773"
  },
  "product": {
    "name": "Crest Straight Leg Joggers",
    "brand": "Gymshark | We Do Gym",
    "sku": "A5A1O",
    "price": 44,
    "currency": "USD",
    "availability": "https://schema.org/InStock",
    "rating": 4.2,
    "review_count": 254
  },
  "content": {
    "headings": [
      {
        "level": "h1",
        "text": "Crest Straight Leg Joggers"
      },
      {
        "level": "h2",
        "text": "Reviews"
      },
      {
        "level": "h2",
        "text": "AVERAGE RATINGSSee more"
      },
      {
        "level": "h2",
        "text": "Recently viewed"
      },
      {
        "level": "h2",
        "text": "Help"
      },
      {
        "level": "h2",
        "text": "My Account"
      },
      {
        "level": "h2",
        "text": "Pages"
      },
      {
        "level": "h2",
        "text": "more about gymshark"
      },
      {
        "level": "h3",
        "text": "EVERYDAY SEAMLESS"
      },
      {
        "level": "h3",
        "text": "ALL NEW COSY LUXE"
      },
      {
        "level": "h3",
        "text": "NEW IN"
      },
      {
        "level": "h3",
        "text": "FOR THE LIFTERS"
      },
      {
        "level": "h3",
        "text": "EVERYDAY SEAMLESS"
      },
      {
        "level": "h3",
        "text": "ALL NEW COSY LUXE"
      },
      {
        "level": "h3",
        "text": "NEW IN"
      },
      {
        "level": "h3",
        "text": "FOR THE LIFTERS"
      },
      {
        "level": "h3",
        "text": "Suuuper Comfy"
      },
      {
        "level": "h3",
        "text": "Comfy rest day pants"
      },
      {
        "level": "h3",
        "text": "Help"
      },
      {
        "level": "h3",
        "text": "My Account"
      },
      {
        "level": "h3",
        "text": "Pages"
      },
      {
        "level": "h4",
        "text": "Gymshark Ribbed Tank 3pk - White/Black/Stone Grey Marl"
      },
      {
        "level": "h4",
        "text": "Gymshark Crest Straight Leg Joggers - Black"
      },
      {
        "level": "h4",
        "text": "Rating snapshot"
      },
      {
        "level": "h5",
        "text": "Trending"
      },
      {
        "level": "h5",
        "text": "Leggings"
      },
      {
        "level": "h5",
        "text": "Products"
      },
      {
        "level": "h5",
        "text": "Explore"
      },
      {
        "level": "h5",
        "text": "Accessories"
      },
      {
        "level": "h5",
        "text": "Last Chance"
      },
      {
        "level": "h5",
        "text": "Featured"
      },
      {
        "level": "h5",
        "text": "Trending"
      },
      {
        "level": "h5",
        "text": "T-shirts & Tops"
      },
      {
        "level": "h5",
        "text": "Products"
      },
      {
        "level": "h5",
        "text": "Explore"
      },
      {
        "level": "h5",
        "text": "Accessories"
      },
      {
        "level": "h5",
        "text": "Last Chance"
      },
      {
        "level": "h5",
        "text": "Featured"
      },
      {
        "level": "h5",
        "text": "Trending"
      },
      {
        "level": "h5",
        "text": "Bags"
      },
      {
        "level": "h5",
        "text": "Equipment"
      },
      {
        "level": "h5",
        "text": "Socks"
      },
      {
        "level": "h5",
        "text": "Underwear"
      },
      {
        "level": "h5",
        "text": "Headwear"
      },
      {
        "level": "h5",
        "text": "Last Chance"
      },
      {
        "level": "h5",
        "text": "Featured"
      },
      {
        "level": "h5",
        "text": "Trending"
      },
      {
        "level": "h5",
        "text": "Leggings"
      },
      {
        "level": "h5",
        "text": "Products"
      },
      {
        "level": "h5",
        "text": "Explore"
      },
      {
        "level": "h5",
        "text": "Accessories"
      },
      {
        "level": "h5",
        "text": "Last Chance"
      },
      {
        "level": "h5",
        "text": "Featured"
      },
      {
        "level": "h5",
        "text": "Trending"
      },
      {
        "level": "h5",
        "text": "T-shirts & Tops"
      },
      {
        "level": "h5",
        "text": "Products"
      },
      {
        "level": "h5",
        "text": "Explore"
      },
      {
        "level": "h5",
        "text": "Accessories"
      },
      {
        "level": "h5",
        "text": "Last Chance"
      },
      {
        "level": "h5",
        "text": "Trending"
      },
      {
        "level": "h5",
        "text": "Bags"
      },
      {
        "level": "h5",
        "text": "Equipment"
      },
      {
        "level": "h5",
        "text": "Socks"
      },
      {
        "level": "h5",
        "text": "Underwear"
      },
      {
        "level": "h5",
        "text": "Headwear"
      },
      {
        "level": "h5",
        "text": "Last Chance"
      },
      {
        "level": "h5",
        "text": "As Seen on Sam Sulek"
      },
      {
        "level": "h5",
        "text": "Size Guide"
      },
      {
        "level": "h5",
        "text": "Stock alerts"
      },
      {
        "level": "h5",
        "text": "Get The Look"
      },
      {
        "level": "h5",
        "text": "Size Guide"
      },
      {
        "level": "h5",
        "text": "Stock alerts"
      },
      {
        "level": "h5",
        "text": "Size Guide"
      },
      {
        "level": "h5",
        "text": "Stock alerts"
      },
      {
        "level": "h5",
        "text": "Description"
      },
      {
        "level": "h5",
        "text": "Description"
      },
      {
        "level": "h5",
        "text": "Delivery & Returns"
      },
      {
        "level": "h5",
        "text": "Delivery & Returns"
      },
      {
        "level": "h5",
        "text": "Get The Look"
      },
      {
        "level": "h5",
        "text": "Gymshark"
      },
      {
        "level": "h5",
        "text": "Gymshark"
      }
    ],
    "features": [
      "Estimated Delivery 4-7working days. *Once your order has shipped.",
      "Free Standard Delivery on orders $75",
      "Gymshark Ribbed Tank 3pk - White/Black/Stone Grey MarlWhite/Black/Stone Grey MarlRegular Price:$28.80",
      "Gymshark Crest Straight Leg Joggers - BlackBlackRegular Price:$44"
    ],
    "specifications": {},
    "word_count": 1414
  },
  "schema_data": [
    {
      "@context": "https://schema.org",
      "@type": "Product",
      "name": "Crest Straight Leg Joggers",
      "image": [
        "https://cdn.shopify.com/s/files/1/0156/6146/files/images-A5A1O_BBBB_1.jpg?v=1753181336"
      ],
      "description": "\nIN YOUR LOCKER\nOur Essential collection takes it back to basics and does it well.\n \n• Adjustable drawcord waist• Side pockets to store your stuff\nSIZE &amp;amp; FIT• Regular fit• Model is 6&apos;0&quot; and wears size M\nMATERIALS &amp;amp; CARE• 80% Cotton, 20% Polyester\nSKU: A5A1O-BBBB",
      "sku": "A5A1O",
      "brand": {
        "@type": "Brand",
        "name": "Gymshark | We Do Gym"
      },
      "offers": {
        "@type": "Offer",
        "url": "https://www.gymshark.com/products/gymshark-crest-straight-leg-joggers-black-aw23",
        "priceCurrency": "USD",
        "price": 44,
        "itemCondition": "https://schema.org/NewCondition",
        "availability": "https://schema.org/InStock",
        "seller": {
          "@type": "Organization",
          "name": "Gymshark | We Do Gym"
        }
      },
      "aggregateRating": {
        "@type": "AggregateRating",
        "ratingValue": 4.2,
        "reviewCount": 254,
        "bestRating": 5,
        "worstRating": 1
      },
      "review": [
        {
          "@type": "Review",
          "author": {
            "@type": "Person",
            "name": "Td10"
          },
          "datePublished": "2026-02-12T20:19:26.000+00:00",
          "description": "Super comfy pants with nice materials and fit. Just ordered a second pair!",
          "reviewRating": {
            "@type": "Rating",
            "bestRating": 5,
            "worstRating": 1,
            "ratingValue": 5
          }
        },
        {
          "@type": "Review",
          "author": {
            "@type": "Person",
            "name": "Freebie"
          },
          "datePublished": "2026-02-04T20:17:25.000+00:00",
          "description": "Really comfortable and good value, just could do with bring an inch longer in the leg.",
          "reviewRating": {
            "@type": "Rating",
            "bestRating": 5,
            "worstRating": 1,
            "ratingValue": 4
          }
        }
      ],
      "category": "pants",
      "color": "Black"
    }
  ],
  "links": {
    "internal": [
      {
        "url": "https://www.gymshark.com/pages/studentbeans",
        "anchor_text": "15% Student Discount ‍🎓"
      },
      {
        "url": "https://www.gymshark.com/blog/article/what-is-the-gymshark-66-challenge",
        "anchor_text": "GYMSHARK66 is back. Change your life in 66 days."
      },
      {
        "url": "https://www.gymshark.com/pages/refer-a-friend",
        "anchor_text": "Refer A Friend To Earn $10 Off Your Next Purchase Of $50+ 👭"
      },
      {
        "url": "https://www.gymshark.com/pages/sign-up-to-our-newsletter",
        "anchor_text": "Get 10% off your first order when you sign up to our emails ✉️"
      },
      {
        "url": "https://www.gymshark.com/pages/commitment-to-accessibility",
        "anchor_text": "Accessibility Statement"
      },
      {
        "url": "https://www.gymshark.com/",
        "anchor_text": ""
      },
      {
        "url": "https://www.gymshark.com/wishlist",
        "anchor_text": ""
      },
      {
        "url": "https://www.gymshark.com/pages/shop-women",
        "anchor_text": "women"
      },
      {
        "url": "https://www.gymshark.com/collections/new-releases/womens",
        "anchor_text": "New Arrivals"
      },
      {
        "url": "https://www.gymshark.com/collections/must-have/womens",
        "anchor_text": "Best Sellers"
      },
      {
        "url": "https://www.gymshark.com/collections/everyday/womens",
        "anchor_text": "Everyday Seamless"
      },
      {
        "url": "https://www.gymshark.com/collections/loungewear/womens",
        "anchor_text": "Cosy Luxe"
      },
      {
        "url": "https://www.gymshark.com/collections/seasonal-colors/womens",
        "anchor_text": "This season’s best shades"
      },
      {
        "url": "https://www.gymshark.com/collections/black-staples/womens",
        "anchor_text": "Black Staples"
      },
      {
        "url": "https://www.gymshark.com/collections/running/womens",
        "anchor_text": "Running"
      },
      {
        "url": "https://www.gymshark.com/collections/leggings/womens",
        "anchor_text": "All Leggings"
      },
      {
        "url": "https://www.gymshark.com/collections/high-waisted-leggings/womens",
        "anchor_text": "High-Waisted Leggings"
      },
      {
        "url": "https://www.gymshark.com/collections/ruched-bum/womens",
        "anchor_text": "Scrunch Butt Leggings"
      },
      {
        "url": "https://www.gymshark.com/collections/black-leggings/womens",
        "anchor_text": "Black Leggings"
      },
      {
        "url": "https://www.gymshark.com/collections/flared-leggings/womens",
        "anchor_text": "Flare Leggings"
      },
      {
        "url": "https://www.gymshark.com/collections/seamless-leggings/womens",
        "anchor_text": "Seamless Leggings"
      },
      {
        "url": "https://www.gymshark.com/collections/leggings-with-pockets/womens",
        "anchor_text": "Leggings With Pockets"
      },
      {
        "url": "https://www.gymshark.com/collections/tall-leggings/womens",
        "anchor_text": "Tall Leggings"
      },
      {
        "url": "https://www.gymshark.com/collections/all-products/womens",
        "anchor_text": "All Products"
      },
      {
        "url": "https://www.gymshark.com/collections/t-shirts-tops/womens",
        "anchor_text": "T-Shirts & Tops"
      },
      {
        "url": "https://www.gymshark.com/collections/sports-bras/womens",
        "anchor_text": "Sports Bras"
      },
      {
        "url": "https://www.gymshark.com/collections/long-sleeve/womens",
        "anchor_text": "Long Sleeves"
      },
      {
        "url": "https://www.gymshark.com/collections/shorts/womens",
        "anchor_text": "Shorts"
      },
      {
        "url": "https://www.gymshark.com/collections/matching-sets/womens",
        "anchor_text": "Matching Sets"
      },
      {
        "url": "https://www.gymshark.com/collections/hoodies/womens",
        "anchor_text": "Hoodies & Sweatshirts"
      },
      {
        "url": "https://www.gymshark.com/collections/zip-jackets/womens",
        "anchor_text": "Jackets"
      },
      {
        "url": "https://www.gymshark.com/collections/joggers/womens",
        "anchor_text": "Joggers & Sweatpants"
      },
      {
        "url": "https://www.gymshark.com/collections/bottoms/womens",
        "anchor_text": "Pants"
      },
      {
        "url": "https://www.gymshark.com/collections/outerwear/womens",
        "anchor_text": "Outerwear"
      },
      {
        "url": "https://www.gymshark.com/collections/tracksuits/womens",
        "anchor_text": "Tracksuits"
      },
      {
        "url": "https://www.gymshark.com/collections/modestwear/womens",
        "anchor_text": "Modest Workout Clothes & Hijabs"
      },
      {
        "url": "https://www.gymshark.com/collections/all-in-one/womens",
        "anchor_text": "Bodysuits"
      },
      {
        "url": "https://www.gymshark.com/pages/leggings-guide",
        "anchor_text": "Leggings Guide"
      },
      {
        "url": "https://www.gymshark.com/pages/sports-bras",
        "anchor_text": "Sports Bra Guide"
      },
      {
        "url": "https://www.gymshark.com/edit",
        "anchor_text": "Your Edit"
      },
      {
        "url": "https://www.gymshark.com/pages/gymshark-loyalty",
        "anchor_text": "Gymshark Loyalty"
      },
      {
        "url": "https://www.gymshark.com/pages/bond-street-store",
        "anchor_text": "Gymshark Bond St"
      },
      {
        "url": "https://www.gymshark.com/collections/accessories",
        "anchor_text": "All Accessories"
      },
      {
        "url": "https://www.gymshark.com/collections/socks",
        "anchor_text": "All Socks"
      },
      {
        "url": "https://www.gymshark.com/collections/last-chance/womens",
        "anchor_text": "For Less"
      },
      {
        "url": "https://www.gymshark.com/pages/shop-men",
        "anchor_text": "men"
      },
      {
        "url": "https://www.gymshark.com/collections/new-releases/mens",
        "anchor_text": "New Arrivals"
      },
      {
        "url": "https://www.gymshark.com/collections/must-have/mens",
        "anchor_text": "Best Sellers"
      },
      {
        "url": "https://www.gymshark.com/collections/carlos-belcast/mens",
        "anchor_text": "Gymshark x Carlos Belcast"
      },
      {
        "url": "https://www.gymshark.com/collections/lifting/mens",
        "anchor_text": "Lifting"
      },
      {
        "url": "https://www.gymshark.com/collections/running/mens",
        "anchor_text": "Running"
      },
      {
        "url": "https://www.gymshark.com/pages/new-users/men",
        "anchor_text": "New to Gymshark?"
      },
      {
        "url": "https://www.gymshark.com/collections/t-shirts-tops/mens",
        "anchor_text": "T-Shirts & Tops"
      },
      {
        "url": "https://www.gymshark.com/collections/compression-fit-shirts/mens",
        "anchor_text": "Compression Fit T-Shirts"
      },
      {
        "url": "https://www.gymshark.com/collections/muscle-fit-shirts/mens",
        "anchor_text": "Muscle Fit Shirts"
      },
      {
        "url": "https://www.gymshark.com/collections/tanks/mens",
        "anchor_text": "Tank Tops"
      },
      {
        "url": "https://www.gymshark.com/collections/oversized-t-shirts/mens",
        "anchor_text": "Oversized T-Shirts"
      },
      {
        "url": "https://www.gymshark.com/collections/long-sleeve/mens",
        "anchor_text": "Long Sleeve Tops"
      },
      {
        "url": "https://www.gymshark.com/collections/stringers/mens",
        "anchor_text": "Stringers"
      },
      {
        "url": "https://www.gymshark.com/collections/black-tops/mens",
        "anchor_text": "Black T-Shirts"
      },
      {
        "url": "https://www.gymshark.com/collections/all-products/mens",
        "anchor_text": "All Products"
      },
      {
        "url": "https://www.gymshark.com/collections/shorts/mens",
        "anchor_text": "Shorts"
      },
      {
        "url": "https://www.gymshark.com/collections/hoodies/mens",
        "anchor_text": "Hoodies & Sweatshirts"
      },
      {
        "url": "https://www.gymshark.com/collections/joggers/mens",
        "anchor_text": "Joggers & Sweatpants"
      },
      {
        "url": "https://www.gymshark.com/collections/bottoms/mens",
        "anchor_text": "Pants"
      },
      {
        "url": "https://www.gymshark.com/collections/tracksuits/mens",
        "anchor_text": "Tracksuits"
      },
      {
        "url": "https://www.gymshark.com/collections/zip-jackets/mens",
        "anchor_text": "Jackets"
      },
      {
        "url": "https://www.gymshark.com/collections/outerwear/mens",
        "anchor_text": "Outerwear"
      },
      {
        "url": "https://www.gymshark.com/collections/underwear/mens",
        "anchor_text": "Men's Underwear & Basics"
      },
      {
        "url": "https://www.gymshark.com/collections/base-layers/mens",
        "anchor_text": "Base Layers"
      },
      {
        "url": "https://www.gymshark.com/pages/mens-shorts-guide",
        "anchor_text": "Shorts Guide"
      },
      {
        "url": "https://www.gymshark.com/collections/last-chance/mens",
        "anchor_text": "For Less"
      },
      {
        "url": "https://www.gymshark.com/collections/new-accessories",
        "anchor_text": "New Arrivals"
      },
      {
        "url": "https://www.gymshark.com/collections/must-have-acc",
        "anchor_text": "Best Sellers"
      },
      {
        "url": "https://www.gymshark.com/collections/seasonal-accessories",
        "anchor_text": "Seasonal Accessories"
      },
      {
        "url": "https://www.gymshark.com/collections/running-accessories",
        "anchor_text": "Running Accessories"
      },
      {
        "url": "https://www.gymshark.com/collections/bags",
        "anchor_text": "All Bags"
      },
      {
        "url": "https://www.gymshark.com/collections/backpacks",
        "anchor_text": "Backpacks"
      },
      {
        "url": "https://www.gymshark.com/collections/duffel-bags",
        "anchor_text": "Duffle Bags"
      },
      {
        "url": "https://www.gymshark.com/collections/tote-bags",
        "anchor_text": "Tote Bags"
      },
      {
        "url": "https://www.gymshark.com/collections/crossbody-bags",
        "anchor_text": "Crossbody Bags"
      },
      {
        "url": "https://www.gymshark.com/collections/small-bags",
        "anchor_text": "Mini Bags"
      },
      {
        "url": "https://www.gymshark.com/collections/keychains",
        "anchor_text": "Bag Accessories"
      },
      {
        "url": "https://www.gymshark.com/collections/equipment",
        "anchor_text": "All Equipment"
      },
      {
        "url": "https://www.gymshark.com/collections/lifting-straps",
        "anchor_text": "Lifting Straps"
      },
      {
        "url": "https://www.gymshark.com/collections/lifting-belts",
        "anchor_text": "Lifting Belts"
      },
      {
        "url": "https://www.gymshark.com/collections/knee-sleeve",
        "anchor_text": "Knee Sleeves"
      },
      {
        "url": "https://www.gymshark.com/collections/bottles",
        "anchor_text": "Bottles & Shakers"
      },
      {
        "url": "https://www.gymshark.com/collections/crew-socks",
        "anchor_text": "Crew Socks"
      },
      {
        "url": "https://www.gymshark.com/collections/quarter-socks",
        "anchor_text": "Quarter Socks"
      },
      {
        "url": "https://www.gymshark.com/collections/trainer-socks",
        "anchor_text": "Trainer Socks"
      },
      {
        "url": "https://www.gymshark.com/collections/graphic-socks",
        "anchor_text": "Graphic Socks"
      },
      {
        "url": "https://www.gymshark.com/collections/headwear",
        "anchor_text": "All Headwear"
      },
      {
        "url": "https://www.gymshark.com/collections/caps",
        "anchor_text": "Caps"
      },
      {
        "url": "https://www.gymshark.com/collections/hijabs",
        "anchor_text": "Hijabs"
      },
      {
        "url": "https://www.gymshark.com/collections/hair-accessories",
        "anchor_text": "Headbands & Hair Accessories"
      },
      {
        "url": "https://www.gymshark.com/collections/last-chance-accessories",
        "anchor_text": "Accessories For Less"
      },
      {
        "url": "https://www.gymshark.com/account",
        "anchor_text": "account"
      },
      {
        "url": "https://www.gymshark.com/blog",
        "anchor_text": "Blog"
      },
      {
        "url": "https://www.gymshark.com/account/register",
        "anchor_text": "Create account"
      },
      {
        "url": "https://www.gymshark.com/products/gymshark-crest-straight-leg-joggers-light-grey-marl-aw23",
        "anchor_text": ""
      },
      {
        "url": "https://www.gymshark.com/products/gymshark-crest-straight-leg-joggers-black-aw23",
        "anchor_text": ""
      },
      {
        "url": "https://www.gymshark.com/products/gymshark-crest-straight-leg-joggers-navy-ss24",
        "anchor_text": ""
      },
      {
        "url": "https://www.gymshark.com/products/gymshark-crest-straight-leg-joggers-pants",
        "anchor_text": ""
      },
      {
        "url": "https://www.gymshark.com/products/gymshark-ribbed-tank-3pk-white-black-stone-grey-marl-ss23",
        "anchor_text": "Gymshark Ribbed Tank 3pk - White/Black/Stone Grey MarlWhite/Black/Stone Grey Marl$28.80"
      },
      {
        "url": "https://www.gymshark.com/pages/submit-a-fake",
        "anchor_text": "Submit a Fake"
      },
      {
        "url": "https://www.gymshark.com/account/login",
        "anchor_text": "Login"
      },
      {
        "url": "https://www.gymshark.com/pages/refer-a-friend?mm_situation=homepage_footer",
        "anchor_text": "Refer a Friend"
      },
      {
        "url": "https://www.gymshark.com/pages/about-us",
        "anchor_text": "About Us"
      },
      {
        "url": "https://www.gymshark.com/blog/article/the-gymshark-training-app-for-ios-and-android",
        "anchor_text": "Training App"
      },
      {
        "url": "https://www.gymshark.com/pages/gymshark-factory-list",
        "anchor_text": "Factory List"
      },
      {
        "url": "https://www.gymshark.com/pages/sustainability",
        "anchor_text": "Sustainability"
      },
      {
        "url": "https://www.gymshark.com/pages/modern-slavery",
        "anchor_text": "Modern Slavery"
      }
    ],
    "external": [
      {
        "url": "https://support.gymshark.com/en-US/article/delivery-information",
        "anchor_text": "Free standard shipping on orders over $75 🚚"
      },
      {
        "url": "https://support.gymshark.com/",
        "anchor_text": "Help"
      },
      {
        "url": "https://support.gymshark.com/en-US/article/klarna",
        "anchor_text": ""
      },
      {
        "url": "https://support.gymshark.com/en-US/article/afterpay",
        "anchor_text": ""
      },
      {
        "url": "https://support.gymshark.com/en-US",
        "anchor_text": "FAQ"
      },
      {
        "url": "https://support.gymshark.com/en-US/article/returns-policy",
        "anchor_text": "Returns Policy"
      },
      {
        "url": "https://us-gymshark.happyreturns.com/",
        "anchor_text": "Make A Return"
      },
      {
        "url": "https://support.gymshark.com/en-US/category/orders-and-delivery",
        "anchor_text": "Orders"
      },
      {
        "url": "https://uk.gymshark.com/pages/stores",
        "anchor_text": "Stores"
      },
      {
        "url": "https://careers.gymshark.com/",
        "anchor_text": "Careers"
      },
      {
        "url": "https://www.veteransadvantage.com/offers/gymshark-honors-you-10-off",
        "anchor_text": "Military Discount"
      },
      {
        "url": "https://discord.gg/gymshark",
        "anchor_text": ""
      },
      {
        "url": "https://www.facebook.com/GymShark",
        "anchor_text": ""
      },
      {
        "url": "https://www.pinterest.com/gymshark",
        "anchor_text": ""
      },
      {
        "url": "https://www.youtube.com/user/GymSharkTV",
        "anchor_text": ""
      },
      {
        "url": "https://www.instagram.com/gymshark",
        "anchor_text": ""
      },
      {
        "url": "https://www.twitter.com/gymshark",
        "anchor_text": ""
      },
      {
        "url": "https://www.tiktok.com/@gymshark",
        "anchor_text": ""
      },
      {
        "url": "https://support.gymshark.com/en-US/pages/terms-and-conditions",
        "anchor_text": "Terms & Conditions"
      },
      {
        "url": "https://support.gymshark.com/en-US/pages/terms-of-use-us",
        "anchor_text": "Terms of Use"
      },
      {
        "url": "https://support.gymshark.com/en-US/pages/privacy-notice-gs",
        "anchor_text": "Privacy Notice"
      },
      {
        "url": "https://support.gymshark.com/en-US/pages/cookie-policy",
        "anchor_text": "Cookie Policy"
      }
    ]
  },
  "trust_signals": {
    "has_return_policy": true,
    "has_refund_policy": false,
    "has_warranty_info": false,
    "has_shipping_info": true,
    "has_cancellation_policy": false,
    "uses_https": true,
    "mentions_secure_payment": false,
    "has_cod_option": false,
    "has_contact_page": false,
    "has_about_page": true,
    "mentions_phone": true,
    "mentions_email": false,
    "mentions_reviews": true,
    "mentions_testimonials": false,
    "official_store_claim": false
  },
  "clean_text": "Gymshark Crest Straight Leg Joggers - Black | Gymshark Pause slide rotation 15% Student Discount ‍🎓 GYMSHARK66 is back. Change your life in 66 days. Free standard shipping on orders over $75 🚚 Refer A Friend To Earn $10 Off Your Next Purchase Of $50+ 👭 Get 10% off your first order when you sign up to our emails ✉️ 15% Student Discount ‍🎓 GYMSHARK66 is back. Change your life in 66 days. Free standard shipping on orders over $75 🚚 Refer A Friend To Earn $10 Off Your Next Purchase Of $50+ 👭 Get 10% off your first order when you sign up to our emails ✉️ 15% Student Discount ‍🎓 Accessibility Statement Skip to content skip to Women women Expand Women Trending New Arrivals Best Sellers Everyday Seamless Cosy Luxe This season’s best shades Black Staples Running Leggings All Leggings High-Waisted Leggings Scrunch Butt Leggings Black Leggings Flare Leggings Seamless Leggings Leggings With Pockets Tall Leggings Products All Products Leggings T-Shirts & Tops Sports Bras Long Sleeves Shorts Matching Sets Hoodies & Sweatshirts Jackets Joggers & Sweatpants Pants Outerwear Tracksuits Modest Workout Clothes & Hijabs Bodysuits Explore Leggings Guide Sports Bra Guide Your Edit Gymshark Loyalty Gymshark Bond St Accessories All Accessories All Socks Last Chance For Less Featured EVERYDAY SEAMLESS ALL NEW COSY LUXE skip to Men men Expand Men Trending New Arrivals Best Sellers Gymshark x Carlos Belcast Lifting Running New to Gymshark? T-shirts & Tops T-Shirts & Tops Compression Fit T-Shirts Muscle Fit Shirts Tank Tops Oversized T-Shirts Long Sleeve Tops Stringers Black T-Shirts Products All Products T-Shirts & Tops Shorts Hoodies & Sweatshirts Joggers & Sweatpants Pants Tracksuits Long Sleeve Tops Jackets Outerwear Men's Underwear & Basics Base Layers Explore Shorts Guide Your Edit Gymshark Loyalty Gymshark Bond St Accessories All Accessories All Socks Last Chance For Less Featured NEW IN FOR THE LIFTERS accessories Expand Accessories Trending All Accessories New Arrivals Best Sellers Seasonal Accessories Running Accessories Bags All Bags Backpacks Duffle Bags Tote Bags Crossbody Bags Mini Bags Bag Accessories Equipment All Equipment Lifting Straps Lifting Belts Knee Sleeves Running Accessories Bottles & Shakers Socks All Socks Crew Socks Quarter Socks Trainer Socks Graphic Socks Underwear Men's Underwear & Basics Headwear All Headwear Caps Hijabs Headbands & Hair Accessories Last Chance Accessories For Less What are you looking for today? Women Men Accessories Featured EVERYDAY SEAMLESS ALL NEW COSY LUXE Trending Leggings Products Explore Accessories Last Chance Featured NEW IN FOR THE LIFTERS Trending T-shirts & Tops Products Explore Accessories Last Chance Trending Bags Equipment Socks Underwear Headwear Last Chance account Accessibility Statement Help Email Sign Up Blog Store Selector dropdown US Australia and New Zealand Bahrain Canada Danmark Deutschland & Österreich Europe Finland France Kuwait Nederland Norge Oman Qatar Rest of World Saudi Schweiz Sverige United Arab Emirates United Kingdom United States Language Selector dropdown English English Español What are you looking for today? Sign in to get exclusive rewards & benefits New Customer? Create account This is an image gallery carousel with clickable slides. Activate any of the buttons to zoom an image. Use Next and Previous buttons to navigate, up or down within the container. Zoom on image Zoom on image Zoom on image Zoom on image Zoom on image Zoom on image Crest Straight Leg Joggers regular fit $44 4.2 ( 254 ) link copied As Seen on Sam Sulek IFBB Pro. Freaky pump specialist. Gymshark athlete. Black Size Guide Size Guide Select a size xs s m l xl xxl 3xl Stock alerts Please select a size Crest Straight Leg Joggers Black l xl xxl 3xl Enter your email, we'll notify you sign up On average 177 reviewers say this product is true to size. Customers say it fits true to size Add to bag Loading... Also available at checkout: Unlock Access to Exclusive Rewards & Benefits Purchasing this product earns 352XP Standard Delivery (4-7 Working Days) Free Standard Delivery for orders over $75 Express Delivery (3 Working Days) Express Delivery Available Get The Look 2 products Get The Look Gymshark Ribbed Tank 3pk - White/Black/Stone Grey Marl White/Black/Stone Grey Marl $28.80 Size Guide Size Guide Select a size xs s m l xl xxl 3xl Stock alerts Please select a size Gymshark Ribbed Tank 3pk - White/Black/Stone Grey Marl White/Black/Stone Grey Marl xs m l xl xxl 3xl Enter your email, we'll notify you sign up Add to bag Gymshark Crest Straight Leg Joggers - Black Black $44 Size Guide Size Guide Select a size xs s m l xl xxl 3xl Stock alerts Please select a size Gymshark Crest Straight Leg Joggers - Black Black l xl xxl 3xl Enter your email, we'll notify you sign up Add to bag Description Description IN YOUR LOCKER Our Essential collection takes it back to basics and does it well. • Adjustable drawcord waist • Side pockets to store your stuff SIZE & FIT • Regular fit • Model is 6'0\" and wears size M MATERIALS & CARE • 80% Cotton, 20% Polyester SKU: A5A1O-BBBB Delivery & Returns Delivery & Returns Standard Shipping - $5 USD Estimated Delivery 4-7 working days. *Once your order has shipped. Free Standard Delivery on orders $75 Express Shipping - $15 USD Estimated delivery 3 working days. *Order by 2pm for same-day processing. Returns Free 30-Day Return Policy, excluding final sale items, underwear, bottles, and swimwear. This is a carousel of products. Use Next and Previous buttons to navigate slides, or use native scroll controls to freely navigate slides. Get The Look Gymshark Ribbed Tank 3pk - White/Black/Stone Grey Marl White/Black/Stone Grey Marl Regular Price: $28.80 Gymshark Crest Straight Leg Joggers - Black Black Regular Price: $44 Reviews 4.2 Based on 254 reviews 87% who purchased would recommend this Rating snapshot 5 ( 169 ) 4 ( 38 ) 3 ( 10 ) 2 ( 8 ) 1 ( 29 ) AVERAGE RATINGS See more Value Very poor OK Excellent Quality 1 Star 3 Star 5 Star Sizing Too tight True to size Too loose Comfort Very uncomfortable Ok Very comfortable Length Too short Spot on Too long reviews.search_label Sort by: Most recent Most recent Oldest first Highest rated Lowest rated Rating Rating 5 Stars 4 Stars 3 Stars 2 Stars 1 Star Activity Activity Weight / strength training (e.g. weight training, weightlifting, bodybuilding, powerlifting) Functional fitness training (e.g. circuits, bootcamp, HIIT) Team sports (e.g. Football, Basketball) Indoor cardio (e.g. treadmill, Stairmaster) Outdoor walking or running Chilling with family or friends Out and about running errands Other Age Age 17 or under 18 - 24 25 - 34 35 - 44 45 - 54 55 - 64 65 or over Workout Frequency Workout Frequency Every day 3 - 6 times a week 1 - 2 times a week Couple of times per month Not regularly Height Height <5ft (152cm) 5ft-5ft3 (153cm-162cm) 5ft4-5ft7 (163cm-172cm) 5ft8-5ft11 (173cm - 182cm) 6ft-6ft3 (183cm-192) 6ft4+(193cm) Td10 Verified buyer 0 0 5 • 9 days ago Suuuper Comfy Super comfy pants with nice materials and fit. Just ordered a second pair! Gymshark Thanks for taking the time to leave a review! It’s great to hear your Gymshark order is on point. We... See more 8 days ago Freebie Verified buyer 1 0 4 • 17 days ago Comfy rest day pants Really comfortable and good value, just could do with bring an inch longer in the leg. Gymshark Thank you for your review! We're delighted to hear that you're enjoying your Gymshark gear. We’re ... See more 16 days ago 1-2 of 254 reviews loading Recently viewed Help Help FAQ Delivery Information Returns Policy Make A Return Orders Submit a Fake FAQ Delivery Information Returns Policy Make A Return Orders Submit a Fake My Account My Account Login Register Login Register Pages Pages Stores Refer a Friend Gymshark Central Gymshark Loyalty About Us Careers Student Discount Training App Military Discount Accessibility Statement Factory List Sustainability Stores Refer a Friend Gymshark Central Gymshark Loyalty About Us Careers Student Discount Training App Military Discount Accessibility Statement Factory List Sustainability more about gymshark Blog 15% Student Discount Email Sign Up Terms & Conditions Terms of Use Privacy Notice Cookie Policy Modern Slavery Store Selector dropdown US Australia and New Zealand Bahrain Canada Danmark Deutschland & Österreich Europe Finland France Kuwait Nederland Norge Oman Qatar Rest of World Saudi Schweiz Sverige United Arab Emirates United Kingdom United States Language Selector dropdown English English Español © 2026 | Gymshark Limited | All Rights Reserved. | We Do Gym."
}